{
  "votes": [
    {
      "bill": "H.R. 7744: Department of Homeland Security Appropriations Act, 2026",
      "question_text": "",
      "date": "2026-03-05",
      "position": "Yea",
      "result": "Passed",
      "chamber": "House",
      "url": "https://www.govtrack.us/congress/votes/119-2026/h87"
    },
    {
      "bill": "On Motion to Recommit: H.R. 7744: Department of Homeland Security Appropriations Act, 2026",
      "question_text": "",
      "date": "2026-03-05",
      "position": "Nay",
      "result": "Failed",
      "chamber": "House",
      "url": "https://www.govtrack.us/congress/votes/119-2026/h86"
    },
    {
      "bill": "H.Con.Res. 38: Directing the President pursuant to section 5(c) of the War Powers Resolution to remove United States Armed Forces from unauthorized hostilities in the Islamic Republic of Iran.",
      "question_text": "",
      "date": "2026-03-05",
      "position": "Nay",
      "result": "Failed",
      "chamber": "House",
      "url": "https://www.govtrack.us/congress/votes/119-2026/h85"
    },
    {
      "bill": "H.Res. 1099: Reaffirming Iran remains the largest state sponsor of terrorism.",
      "question_text": "",
      "date": "2026-03-05",
      "position": "Yea",
      "result": "Passed",
      "chamber": "House",
      "url": "https://www.govtrack.us/congress/votes/119-2026/h84"
    },
    {
      "bill": "On Motion to Refer: H.Res. 1100: Directing the Committee on Ethics to preserve and publicly release records of the \u2026",
      "question_text": "",
      "date": "2026-03-04",
      "position": "Yea",
      "result": "Passed",
      "chamber": "House",
      "url": "https://www.govtrack.us/congress/votes/119-2026/h83"
    },
    {
      "bill": "H.R. 6472: Territorial Student Access to Higher Education Act",
      "question_text": "",
      "date": "2026-03-04",
      "position": "Yea",
      "result": "Passed",
      "chamber": "House",
      "url": "https://www.govtrack.us/congress/votes/119-2026/h82"
    },
    {
      "bill": "S. 723: Tribal Trust Land Homeownership Act of 2025",
      "question_text": "",
      "date": "2026-03-04",
      "position": "Yea",
      "result": "Passed",
      "chamber": "House",
      "url": "https://www.govtrack.us/congress/votes/119-2026/h81"
    },
    {
      "bill": "H.Res. 1095: Providing for consideration of the bill (H.R. 7744) making appropriations for the Department of Homeland Security for the fiscal year ending September 30, 2026, and for other purposes.",
      "question_text": "",
      "date": "2026-03-04",
      "position": "Aye",
      "result": "Passed",
      "chamber": "House",
      "url": "https://www.govtrack.us/congress/votes/119-2026/h80"
    },
    {
      "bill": "On Ordering the Previous Question: H.Res. 1095: Providing for consideration of the bill (H.R. 7744) making appropriations for the Department \u2026",
      "question_text": "",
      "date": "2026-03-04",
      "position": "Yea",
      "result": "Passed",
      "chamber": "House",
      "url": "https://www.govtrack.us/congress/votes/119-2026/h79"
    },
    {
      "bill": "H.R. 4758: Homeowner Energy Freedom Act",
      "question_text": "",
      "date": "2026-02-25",
      "position": "Yea",
      "result": "Passed",
      "chamber": "House",
      "url": "https://www.govtrack.us/congress/votes/119-2026/h78"
    },
    {
      "bill": "On Motion to Recommit: H.R. 4758: Homeowner Energy Freedom Act",
      "question_text": "",
      "date": "2026-02-25",
      "position": "Not Voting",
      "result": "Failed",
      "chamber": "House",
      "url": "https://www.govtrack.us/congress/votes/119-2026/h77"
    },
    {
      "bill": "H.R. 4626: Home Appliance Protection and Affordability Act",
      "question_text": "",
      "date": "2026-02-24",
      "position": "Yea",
      "result": "Passed",
      "chamber": "House",
      "url": "https://www.govtrack.us/congress/votes/119-2026/h76"
    },
    {
      "bill": "On Motion to Recommit: H.R. 4626: Home Appliance Protection and Affordability Act",
      "question_text": "",
      "date": "2026-02-24",
      "position": "Nay",
      "result": "Failed",
      "chamber": "House",
      "url": "https://www.govtrack.us/congress/votes/119-2026/h75"
    },
    {
      "bill": "H.Res. 1075: Providing for consideration of the bill (H.R. 4626) to amend the Energy Policy and Conservation Act to prohibit the Secretary of Energy from prescribing any new or amended energy conservation standard for a product that is not technologicall",
      "question_text": "",
      "date": "2026-02-24",
      "position": "Aye",
      "result": "Passed",
      "chamber": "House",
      "url": "https://www.govtrack.us/congress/votes/119-2026/h74"
    },
    {
      "bill": "On Ordering the Previous Question: H.Res. 1075: Providing for consideration of the bill (H.R. 4626) to amend the Energy Policy \u2026",
      "question_text": "",
      "date": "2026-02-24",
      "position": "Yea",
      "result": "Passed",
      "chamber": "House",
      "url": "https://www.govtrack.us/congress/votes/119-2026/h73"
    },
    {
      "bill": "S. 2503: ROTOR Act",
      "question_text": "",
      "date": "2026-02-24",
      "position": "Nay",
      "result": "Failed",
      "chamber": "House",
      "url": "https://www.govtrack.us/congress/votes/119-2026/h72"
    },
    {
      "bill": "H.R. 6329: Information Quality Assurance Act of 2025",
      "question_text": "",
      "date": "2026-02-24",
      "position": "Not Voting",
      "result": "Passed",
      "chamber": "House",
      "url": "https://www.govtrack.us/congress/votes/119-2026/h71"
    },
    {
      "bill": "H.R. 2189: Law-Enforcement Innovate to De-Escalate Act",
      "question_text": "",
      "date": "2026-02-12",
      "position": "Yea",
      "result": "Passed",
      "chamber": "House",
      "url": "https://www.govtrack.us/congress/votes/119-2026/h70"
    },
    {
      "bill": "S. 1383: Safeguard American Voter Eligibility Act",
      "question_text": "",
      "date": "2026-02-11",
      "position": "Yea",
      "result": "Passed",
      "chamber": "House",
      "url": "https://www.govtrack.us/congress/votes/119-2026/h69"
    },
    {
      "bill": "On Motion to Commit: S. 1383: Safeguard American Voter Eligibility Act",
      "question_text": "",
      "date": "2026-02-11",
      "position": "Nay",
      "result": "Failed",
      "chamber": "House",
      "url": "https://www.govtrack.us/congress/votes/119-2026/h68"
    }
  ],
  "govtrack_id": 412698,
  "votes_updated": "2026-03-13T05:44:16.389638",
  "votes_status": "ok",
  "id": "M001199",
  "name": "Brian J. Mast",
  "party": "Republican",
  "state": "Florida",
  "district": "21",
  "chamber": "House",
  "photo_url": "https://bioguide.congress.gov/bioguide/photo/M/M001199.jpg",
  "term_start": "2017-01-01",
  "score": 0,
  "flags": [],
  "updated": "2026-03-13T05:39:50.958616",
  "corporate_insider_signals": 0,
  "edgar_signal_type": "corporate_insider",
  "fec_candidate_id": "H6FL18097",
  "total_raised": 2368244.0,
  "total_spent": 1838067.47,
  "pac_contributions": 0,
  "individual_contributions": 1189989.16,
  "cash_on_hand": "2301554.19",
  "total_raised_display": "$2.4M",
  "data_updated": "2026-03-13T06:33:00.468156",
  "last_updated": "2026-03-13T06:33:00.468156",
  "bills": [
    {
      "bill_id": "HRES1099-119",
      "title": "Reaffirming Iran remains the largest state sponsor of terrorism.",
      "type": "HRES",
      "number": "1099",
      "congress": 119,
      "introduced_date": "2026-03-04",
      "latest_action": "Motion to reconsider laid on the table Agreed to without objection.",
      "url": "https://api.congress.gov/v3/bill/119/hres/1099?format=json",
      "keywords": [
        "iran",
        "iranian",
        "responsible",
        "american",
        "regime",
        "continues",
        "html",
        "body",
        "pre",
        "government",
        "res",
        "islamic",
        "republic",
        "largest",
        "state",
        "sponsor",
        "terrorism",
        "support",
        "deaths",
        "citizens"
      ],
      "has_text": true,
      "similarity_score": null,
      "match_type": null,
      "alec_match": null,
      "similar_member_bills": [],
      "cosponsors": [
        "H001093",
        "I000056"
      ],
      "donor_interest": {
        "match": false,
        "matched_industries": [],
        "keyword_hits": {}
      }
    },
    {
      "bill_id": "HCONRES74-119",
      "title": "Providing for a joint session of Congress to receive a message from the President.",
      "type": "HCONRES",
      "number": "74",
      "congress": 119,
      "introduced_date": "2026-02-10",
      "latest_action": "Message on Senate action sent to the House.",
      "url": "https://api.congress.gov/v3/bill/119/hconres/74?format=json",
      "keywords": [
        "html",
        "body",
        "pre",
        "con",
        "res",
        "february",
        "two",
        "attest",
        "congressional",
        "bills",
        "government",
        "publishing",
        "office",
        "enrolled",
        "bill",
        "enr",
        "agreed",
        "one",
        "hundred",
        "nineteenth"
      ],
      "has_text": true,
      "similarity_score": null,
      "match_type": "member_bill",
      "alec_match": null,
      "similar_member_bills": [
        {
          "bill_id": "HCONRES93-118",
          "sponsor_id": "S001176",
          "similarity_score": 0.942
        }
      ],
      "cosponsors": [],
      "donor_interest": {
        "match": false,
        "matched_industries": [],
        "keyword_hits": {}
      }
    },
    {
      "bill_id": "HR7438-119",
      "title": "PETSAFE Act of 2026",
      "type": "HR",
      "number": "7438",
      "congress": 119,
      "introduced_date": "2026-02-09",
      "latest_action": "Referred to the House Committee on Transportation and Infrastructure.",
      "url": "https://api.congress.gov/v3/bill/119/hr/7438?format=json",
      "keywords": [
        "emergency",
        "response",
        "companion",
        "management",
        "preparedness",
        "animals",
        "animal",
        "supplies",
        "post",
        "katrina",
        "reform",
        "disaster",
        "assistance",
        "support",
        "equipment",
        "html",
        "body",
        "pre",
        "government",
        "introduced"
      ],
      "has_text": true,
      "similarity_score": null,
      "match_type": null,
      "alec_match": null,
      "similar_member_bills": [],
      "cosponsors": [
        "B001260",
        "T000468",
        "C001080",
        "S001231",
        "C001125",
        "M001217",
        "B001257",
        "K000391",
        "W000797",
        "S000522"
      ],
      "donor_interest": {
        "match": false,
        "matched_industries": [],
        "keyword_hits": {}
      }
    },
    {
      "bill_id": "HR6875-119",
      "title": "AI OVERWATCH Act",
      "type": "HR",
      "number": "6875",
      "congress": 119,
      "introduced_date": "2025-12-18",
      "latest_action": "Referred to the House Committee on Foreign Affairs.",
      "url": "https://api.congress.gov/v3/bill/119/hr/6875?format=json",
      "keywords": [
        "integrated",
        "covered",
        "export",
        "circuit",
        "country",
        "license",
        "concern",
        "secretary",
        "circuits",
        "security",
        "committee",
        "transfer",
        "policy",
        "control",
        "headquartered",
        "person",
        "intelligence",
        "performance",
        "operating",
        "ultimate"
      ],
      "has_text": true,
      "similarity_score": null,
      "match_type": null,
      "alec_match": null,
      "similar_member_bills": [],
      "cosponsors": [
        "H001058",
        "M001194",
        "K000397",
        "S001224",
        "C001087",
        "L000585",
        "M001157",
        "D000626",
        "K000398",
        "M001219"
      ],
      "donor_interest": {
        "match": false,
        "matched_industries": [],
        "keyword_hits": {}
      }
    },
    {
      "bill_id": "HCONRES67-119",
      "title": "Authorizing the use of the rotunda of the Capitol for the lying in state of the remains of Sergeant Edgar Brian Torres-Tovar, and of Sergeant William Nathaniel Howard, of the Iowa National Guard.",
      "type": "HCONRES",
      "number": "67",
      "congress": 119,
      "introduced_date": "2025-12-15",
      "latest_action": "Referred to the House Committee on House Administration.",
      "url": "https://api.congress.gov/v3/bill/119/hconres/67?format=json",
      "keywords": [
        "sergeant",
        "capitol",
        "iowa",
        "rotunda",
        "state",
        "remains",
        "edgar",
        "brian",
        "torres",
        "tovar",
        "william",
        "nathaniel",
        "howard",
        "national",
        "guard",
        "html",
        "body",
        "pre",
        "con",
        "res"
      ],
      "has_text": true,
      "similarity_score": null,
      "match_type": null,
      "alec_match": null,
      "similar_member_bills": [],
      "cosponsors": [
        "N000193",
        "F000446",
        "M001215",
        "H001091"
      ],
      "donor_interest": {
        "match": false,
        "matched_industries": [],
        "keyword_hits": {}
      }
    },
    {
      "bill_id": "HR6691-119",
      "title": "Ceasing Age-Based Trucking Restrictions Act",
      "type": "HR",
      "number": "6691",
      "congress": 119,
      "introduced_date": "2025-12-12",
      "latest_action": "Referred to the House Committee on Transportation and Infrastructure.",
      "url": "https://api.congress.gov/v3/bill/119/hr/6691?format=json",
      "keywords": [
        "transportation",
        "port",
        "goods",
        "code",
        "state",
        "entry",
        "another",
        "place",
        "within",
        "interstate",
        "purposes",
        "treatment",
        "html",
        "body",
        "pre",
        "introduced",
        "provide",
        "constitute",
        "bill",
        "adding"
      ],
      "has_text": true,
      "similarity_score": null,
      "match_type": null,
      "alec_match": null,
      "similar_member_bills": [],
      "cosponsors": [],
      "donor_interest": {
        "match": false,
        "matched_industries": [],
        "keyword_hits": {}
      }
    },
    {
      "bill_id": "HR6044-119",
      "title": "Pay Our Patriots Act",
      "type": "HR",
      "number": "6044",
      "congress": 119,
      "introduced_date": "2025-11-13",
      "latest_action": "Referred to the Subcommittee on Aviation.",
      "url": "https://api.congress.gov/v3/bill/119/hr/6044?format=json",
      "keywords": [
        "appropriations",
        "covered",
        "pay",
        "lapse",
        "allowances",
        "armed",
        "forces",
        "federal",
        "aviation",
        "administration",
        "provide",
        "continuing",
        "essential",
        "employees",
        "available",
        "appropriated",
        "secretary",
        "employee",
        "html",
        "body"
      ],
      "has_text": true,
      "similarity_score": null,
      "match_type": null,
      "alec_match": null,
      "similar_member_bills": [],
      "cosponsors": [
        "E000235",
        "K000397"
      ],
      "donor_interest": {
        "match": false,
        "matched_industries": [],
        "keyword_hits": {}
      }
    },
    {
      "bill_id": "HRES733-119",
      "title": "Expressing support for the designation of the week of September 20 through September 27, 2025, as \"National Estuaries Week\".",
      "type": "HRES",
      "number": "733",
      "congress": 119,
      "introduced_date": "2025-09-17",
      "latest_action": "Referred to the House Committee on Natural Resources.",
      "url": "https://api.congress.gov/v3/bill/119/hres/733?format=json",
      "keywords": [
        "estuaries",
        "percent",
        "national",
        "week",
        "september",
        "fish",
        "water",
        "coastal",
        "jobs",
        "economic",
        "recreational",
        "restore",
        "government",
        "support",
        "estuarine",
        "health",
        "protect",
        "designation",
        "natural",
        "estuary"
      ],
      "has_text": true,
      "similarity_score": null,
      "match_type": null,
      "alec_match": null,
      "similar_member_bills": [],
      "cosponsors": [
        "H001099",
        "B001278",
        "L000560",
        "G000559",
        "M001225",
        "S001159",
        "M001196",
        "L000598",
        "L000599",
        "D000230"
      ],
      "donor_interest": {
        "match": false,
        "matched_industries": [],
        "keyword_hits": {}
      }
    },
    {
      "bill_id": "HR5300-119",
      "title": "Department of State Policy Provisions Act",
      "type": "HR",
      "number": "5300",
      "congress": 119,
      "introduced_date": "2025-09-11",
      "latest_action": "Ordered to be Reported (Amended) by the Yeas and Nays: 27 - 24.",
      "url": "https://api.congress.gov/v3/bill/119/hr/5300?format=json",
      "keywords": [
        "secretary",
        "foreign",
        "department",
        "report",
        "program",
        "country",
        "security",
        "committee",
        "congressional",
        "affairs",
        "appropriate",
        "notification",
        "covered",
        "state",
        "requirement",
        "committees",
        "general",
        "diplomatic",
        "management",
        "required"
      ],
      "has_text": true,
      "similarity_score": null,
      "match_type": null,
      "alec_match": null,
      "similar_member_bills": [],
      "cosponsors": [],
      "donor_interest": {
        "match": false,
        "matched_industries": [],
        "keyword_hits": {}
      }
    },
    {
      "bill_id": "HR5299-119",
      "title": "DFC Modernization Act of 2025",
      "type": "HR",
      "number": "5299",
      "congress": 119,
      "introduced_date": "2025-09-11",
      "latest_action": "Ordered to be Reported (Amended) by the Yeas and Nays: 28 - 23.",
      "url": "https://api.congress.gov/v3/bill/119/hr/5299?format=json",
      "keywords": [
        "development",
        "investments",
        "striking",
        "better",
        "utilization",
        "leading",
        "countries",
        "corporation",
        "inserting",
        "country",
        "equity",
        "support",
        "private",
        "security",
        "end",
        "policy",
        "economic",
        "energy",
        "subparagraph",
        "enterprise"
      ],
      "has_text": true,
      "similarity_score": null,
      "match_type": null,
      "alec_match": null,
      "similar_member_bills": [],
      "cosponsors": [],
      "donor_interest": {
        "match": false,
        "matched_industries": [],
        "keyword_hits": {}
      }
    }
  ],
  "bills_updated": "2026-03-11T08:44:36.444999+00:00",
  "bills_count": 10,
  "donor_alignment_score": 0.0,
  "alec_match_count": 0,
  "donor_match_count": 0,
  "edgar_status": "unresolved"
}