{
  "votes": [
    {
      "bill": "Motion to Invoke Cloture: Lt. Gen. Joshua M. Ruud to be General in the United States Army: Lt. Gen. Joshua M. Rudd, in the Army, to be General",
      "question_text": "",
      "date": "2026-03-09",
      "position": "Yea",
      "result": "Cloture Motion Agreed to",
      "chamber": "Senate",
      "url": "https://www.govtrack.us/congress/votes/119-2026/s48"
    },
    {
      "bill": "Upon Reconsideration, Motion to Invoke Cloture: Motion to Proceed to H.R. 7147",
      "question_text": "",
      "date": "2026-03-05",
      "position": "Yea",
      "result": "Cloture on the Motion to Proceed Rejected",
      "chamber": "Senate",
      "url": "https://www.govtrack.us/congress/votes/119-2026/s47"
    },
    {
      "bill": "On the Motion to Discharge S.J.Res. 104",
      "question_text": "",
      "date": "2026-03-04",
      "position": "Nay",
      "result": "Motion to Discharge Rejected",
      "chamber": "Senate",
      "url": "https://www.govtrack.us/congress/votes/119-2026/s46"
    },
    {
      "bill": "Motion to Proceed on H.R. 6644: Housing for the 21st Century Act",
      "question_text": "",
      "date": "2026-03-04",
      "position": "Nay",
      "result": "Motion to Proceed Agreed to",
      "chamber": "Senate",
      "url": "https://www.govtrack.us/congress/votes/119-2026/s45"
    },
    {
      "bill": "Motion to Invoke Cloture: Motion to Proceed to H.R. 6644",
      "question_text": "",
      "date": "2026-03-02",
      "position": "Nay",
      "result": "Cloture on the Motion to Proceed Agreed to",
      "chamber": "Senate",
      "url": "https://www.govtrack.us/congress/votes/119-2026/s44"
    },
    {
      "bill": "On the Nomination PN730-46: Ryan McCormack, of Virginia, to be Under Secretary of Transportation for Policy",
      "question_text": "",
      "date": "2026-02-26",
      "position": "Yea",
      "result": "Nomination Confirmed",
      "chamber": "Senate",
      "url": "https://www.govtrack.us/congress/votes/119-2026/s43"
    },
    {
      "bill": "Motion to Invoke Cloture: Ryan McCormack to be Under Secretary of Transportation for Policy: Ryan McCormack, of Virginia, to be Under Secretary of Transportation for Policy",
      "question_text": "",
      "date": "2026-02-26",
      "position": "Yea",
      "result": "Cloture Motion Agreed to",
      "chamber": "Senate",
      "url": "https://www.govtrack.us/congress/votes/119-2026/s42"
    },
    {
      "bill": "On the Nomination PN730-19: John DeLeeuw, of Texas, to be a Member of the National Transportation Safety Board for the remainder of the term expiring December 31, 2026",
      "question_text": "",
      "date": "2026-02-25",
      "position": "Yea",
      "result": "Nomination Confirmed",
      "chamber": "Senate",
      "url": "https://www.govtrack.us/congress/votes/119-2026/s41"
    },
    {
      "bill": "Motion to Invoke Cloture: John DeLeeuw to be a Member of the National Transportation Safety Board: John DeLeeuw, of Texas, to be a Member of the National Transportation Safety Board for the remainder of the term expiring December 31, 2026",
      "question_text": "",
      "date": "2026-02-25",
      "position": "Yea",
      "result": "Cloture Motion Agreed to",
      "chamber": "Senate",
      "url": "https://www.govtrack.us/congress/votes/119-2026/s40"
    },
    {
      "bill": "Motion to Invoke Cloture: Motion to Proceed to H.R. 7147",
      "question_text": "",
      "date": "2026-02-24",
      "position": "Yea",
      "result": "Cloture on the Motion to Proceed Rejected",
      "chamber": "Senate",
      "url": "https://www.govtrack.us/congress/votes/119-2026/s39"
    },
    {
      "bill": "Motion to Invoke Cloture: Motion to Proceed to H.R. 7147",
      "question_text": "",
      "date": "2026-02-12",
      "position": "Yea",
      "result": "Cloture Motion Rejected",
      "chamber": "Senate",
      "url": "https://www.govtrack.us/congress/votes/119-2026/s38"
    },
    {
      "bill": "H.J.Res. 142: Disapproving the action of the District of Columbia Council in approving the D.C. Income and Franchise Tax Conformity and Revision Temporary Amendment Act of 2025.",
      "question_text": "",
      "date": "2026-02-12",
      "position": "Yea",
      "result": "Joint Resolution Passed",
      "chamber": "Senate",
      "url": "https://www.govtrack.us/congress/votes/119-2026/s37"
    },
    {
      "bill": "Motion to Proceed on H.J.Res. 142: Disapproving the action of the District of Columbia Council in approving the D.C. Income and Franchise Tax Conformity and Revision Temporary Amendment Act of 2025.",
      "question_text": "",
      "date": "2026-02-11",
      "position": "Yea",
      "result": "Motion to Proceed Agreed to",
      "chamber": "Senate",
      "url": "https://www.govtrack.us/congress/votes/119-2026/s36"
    },
    {
      "bill": "Motion to Proceed on S.J.Res. 95: A joint resolution providing for congressional disapproval under chapter 8 of title 5, United States Code, of the rule submitted by the Internal Revenue Service relating to \u201cInterim Guidance Simplifying Application of the Corporate Alternati",
      "question_text": "",
      "date": "2026-02-10",
      "position": "Nay",
      "result": "Motion to Proceed Rejected",
      "chamber": "Senate",
      "url": "https://www.govtrack.us/congress/votes/119-2026/s35"
    },
    {
      "bill": "On the Nomination PN726-4: Daniel E. Burrows, of Colorado, to be an Assistant Attorney General",
      "question_text": "",
      "date": "2026-02-10",
      "position": "Yea",
      "result": "Nomination Confirmed",
      "chamber": "Senate",
      "url": "https://www.govtrack.us/congress/votes/119-2026/s34"
    },
    {
      "bill": "Motion to Invoke Cloture: Daniel E. Burrows to be an Assistant Attorney General: Daniel E. Burrows, of Colorado, to be an Assistant Attorney General",
      "question_text": "",
      "date": "2026-02-09",
      "position": "Yea",
      "result": "Cloture Motion Agreed to",
      "chamber": "Senate",
      "url": "https://www.govtrack.us/congress/votes/119-2026/s33"
    },
    {
      "bill": "On the Nomination PN726-11: Justin R. Olson, of Indiana, to be United States District Judge for the Southern District of Indiana",
      "question_text": "",
      "date": "2026-02-05",
      "position": "Yea",
      "result": "Nomination Confirmed",
      "chamber": "Senate",
      "url": "https://www.govtrack.us/congress/votes/119-2026/s32"
    },
    {
      "bill": "Motion to Invoke Cloture: Justin R. Olson to be U.S. District Judge for the Southern District of Indiana: Justin R. Olson, of Indiana, to be United States District Judge for the Southern District of Indiana",
      "question_text": "",
      "date": "2026-02-05",
      "position": "Yea",
      "result": "Cloture Motion Agreed to",
      "chamber": "Senate",
      "url": "https://www.govtrack.us/congress/votes/119-2026/s31"
    },
    {
      "bill": "On the Nomination PN726-9: Brian Charles Lea, of Tennessee, to be United States District Judge for the Western District of Tennessee",
      "question_text": "",
      "date": "2026-02-05",
      "position": "Yea",
      "result": "Nomination Confirmed",
      "chamber": "Senate",
      "url": "https://www.govtrack.us/congress/votes/119-2026/s30"
    },
    {
      "bill": "Motion to Invoke Cloture: Brian Charles Lea to be U.S. District Judge for the Western District of Tennessee: Brian Charles Lea, of Tennessee, to be United States District Judge for the Western District of Tennessee",
      "question_text": "",
      "date": "2026-02-04",
      "position": "Yea",
      "result": "Cloture Motion Agreed to",
      "chamber": "Senate",
      "url": "https://www.govtrack.us/congress/votes/119-2026/s29"
    }
  ],
  "govtrack_id": 412838,
  "votes_updated": "2026-03-10T05:34:36.925822",
  "votes_status": "ok",
  "id": "S001217",
  "name": "Rick Scott",
  "party": "Republican",
  "state": "Florida",
  "district": "",
  "chamber": "Senate",
  "photo_url": "https://bioguide.congress.gov/bioguide/photo/S/S001217.jpg",
  "term_start": "2019-01-01",
  "score": 0,
  "flags": [],
  "updated": "2026-03-10T05:37:47.714614",
  "corporate_insider_signals": 0,
  "edgar_signal_type": "corporate_insider",
  "fec_candidate_id": "S8FL00273",
  "total_raised_display": "$0",
  "data_updated": "2026-03-10T06:07:09.950028",
  "last_updated": "2026-03-10T06:07:09.950028",
  "bills": [
    {
      "bill_id": "S4024-119",
      "title": "A bill to strengthen oversight, accountability, and recovery of Federal funds administered through State block grants and other pass-through mechanisms, and for other purposes.",
      "type": "S",
      "number": "4024",
      "congress": 119,
      "introduced_date": "2026-03-05",
      "latest_action": "Read twice and referred to the Committee on the Judiciary.",
      "url": "https://api.congress.gov/v3/bill/119/s/4024?format=json",
      "keywords": [
        "obj",
        "endobj",
        "type",
        "font",
        "fontdescriptor",
        "subtype",
        "basefont",
        "encoding",
        "firstchar",
        "lastchar",
        "widths",
        "filter",
        "flatedecode",
        "length",
        "stream",
        "endstream",
        "pdf",
        "extgstate",
        "contents",
        "parent"
      ],
      "has_text": true,
      "similarity_score": null,
      "match_type": "member_bill",
      "alec_match": null,
      "similar_member_bills": [
        {
          "bill_id": "S3990-119",
          "sponsor_id": "S001203",
          "similarity_score": 0.999
        },
        {
          "bill_id": "S3928-119",
          "sponsor_id": "S001150",
          "similarity_score": 0.991
        },
        {
          "bill_id": "S3975-119",
          "sponsor_id": "Y000064",
          "similarity_score": 0.989
        }
      ],
      "cosponsors": [],
      "donor_interest": {
        "match": false,
        "matched_industries": [],
        "keyword_hits": {}
      }
    },
    {
      "bill_id": "SRES627-119",
      "title": "A resolution designating March 5, 2026, as \"National Slam the Scam Day\" to raise awareness about pervasive scams and to prevent government imposter scams and other types of scams by promoting education about such scams.",
      "type": "SRES",
      "number": "627",
      "congress": 119,
      "introduced_date": "2026-03-05",
      "latest_action": "Referred to the Committee on the Judiciary. (text: CR S887-888)",
      "url": "https://api.congress.gov/v3/bill/119/sres/627?format=json",
      "keywords": [
        "scams",
        "government",
        "imposter",
        "individuals",
        "federal",
        "trade",
        "commission",
        "people",
        "agencies",
        "march",
        "national",
        "slam",
        "scam",
        "day",
        "awareness",
        "social",
        "service",
        "adults",
        "reported",
        "raise"
      ],
      "has_text": true,
      "similarity_score": null,
      "match_type": null,
      "alec_match": null,
      "similar_member_bills": [],
      "cosponsors": [
        "K000377",
        "G000555",
        "W000790",
        "B001277",
        "C001035",
        "B001243",
        "R000605",
        "M001244"
      ],
      "donor_interest": {
        "match": false,
        "matched_industries": [],
        "keyword_hits": {}
      }
    },
    {
      "bill_id": "S3951-119",
      "title": "A bill to provide authority and discretion to the President over budgetary resources to achieve a balanced budget.",
      "type": "S",
      "number": "3951",
      "congress": 119,
      "introduced_date": "2026-02-26",
      "latest_action": "Read twice and referred to the Committee on the Budget.",
      "url": "https://api.congress.gov/v3/bill/119/s/3951?format=json",
      "keywords": [],
      "has_text": false,
      "similarity_score": null,
      "match_type": null,
      "alec_match": null,
      "similar_member_bills": [],
      "cosponsors": [],
      "donor_interest": {
        "match": false,
        "matched_industries": [],
        "keyword_hits": {}
      }
    },
    {
      "bill_id": "S3920-119",
      "title": "A bill to strengthen homeland security by expanding Urban Areas Security Initiative grant eligibility criteria to promote cooperation with U.S. Immigration and Customs Enforcement and to advance election security protections.",
      "type": "S",
      "number": "3920",
      "congress": 119,
      "introduced_date": "2026-02-25",
      "latest_action": "Read twice and referred to the Committee on Homeland Security and Governmental Affairs.",
      "url": "https://api.congress.gov/v3/bill/119/s/3920?format=json",
      "keywords": [],
      "has_text": false,
      "similarity_score": null,
      "match_type": null,
      "alec_match": null,
      "similar_member_bills": [],
      "cosponsors": [],
      "donor_interest": {
        "match": false,
        "matched_industries": [],
        "keyword_hits": {}
      }
    },
    {
      "bill_id": "S3921-119",
      "title": "A bill to establish eligibility requirements for the use of Federal funds for Special Event Assessment Rating support in sanctuary jurisdictions and to reallocate such funds to U.S. Immigration and Customs Enforcement for immigration enforcement efforts.",
      "type": "S",
      "number": "3921",
      "congress": 119,
      "introduced_date": "2026-02-25",
      "latest_action": "Read twice and referred to the Committee on Homeland Security and Governmental Affairs.",
      "url": "https://api.congress.gov/v3/bill/119/s/3921?format=json",
      "keywords": [
        "obj",
        "endobj",
        "filter",
        "flatedecode",
        "length",
        "stream",
        "endstream",
        "contents",
        "parent",
        "resources",
        "type",
        "page",
        "wms",
        "tmu",
        "umt",
        "pdf",
        "jql",
        "ktq",
        "jbc",
        "jakp"
      ],
      "has_text": true,
      "similarity_score": null,
      "match_type": "member_bill",
      "alec_match": null,
      "similar_member_bills": [
        {
          "bill_id": "S3964-119",
          "sponsor_id": "S001232",
          "similarity_score": 0.999
        },
        {
          "bill_id": "S3912-119",
          "sponsor_id": "S001232",
          "similarity_score": 0.999
        }
      ],
      "cosponsors": [
        "M001242"
      ],
      "donor_interest": {
        "match": false,
        "matched_industries": [],
        "keyword_hits": {}
      }
    },
    {
      "bill_id": "SRES607-119",
      "title": "A resolution honoring the memories of the victims of the senseless attack at Marjory Stoneman Douglas High School on February 14, 2018.",
      "type": "SRES",
      "number": "607",
      "congress": 119,
      "introduced_date": "2026-02-12",
      "latest_action": "Referred to the Committee on the Judiciary. (text: CR S612)",
      "url": "https://api.congress.gov/v3/bill/119/sres/607?format=json",
      "keywords": [
        "attack",
        "february",
        "victims",
        "marjory",
        "stoneman",
        "douglas",
        "high",
        "school",
        "memories",
        "senseless",
        "parkland",
        "community",
        "html",
        "body",
        "pre",
        "res",
        "honoring",
        "florida",
        "resolution",
        "took"
      ],
      "has_text": true,
      "similarity_score": null,
      "match_type": null,
      "alec_match": null,
      "similar_member_bills": [],
      "cosponsors": [
        "M001244"
      ],
      "donor_interest": {
        "match": false,
        "matched_industries": [],
        "keyword_hits": {}
      }
    },
    {
      "bill_id": "S3857-119",
      "title": "One Nation, One Visa Policy Act",
      "type": "S",
      "number": "3857",
      "congress": 119,
      "introduced_date": "2026-02-12",
      "latest_action": "Read twice and referred to the Committee on the Judiciary.",
      "url": "https://api.congress.gov/v3/bill/119/s/3857?format=json",
      "keywords": [
        "people",
        "republic",
        "china",
        "visa",
        "security",
        "immigration",
        "homeland",
        "national",
        "valid",
        "secretary",
        "program",
        "laws",
        "html",
        "body",
        "pre",
        "introduced",
        "prohibit",
        "admitting",
        "purposes",
        "bill"
      ],
      "has_text": true,
      "similarity_score": null,
      "match_type": null,
      "alec_match": null,
      "similar_member_bills": [],
      "cosponsors": [],
      "donor_interest": {
        "match": false,
        "matched_industries": [],
        "keyword_hits": {}
      }
    },
    {
      "bill_id": "S3856-119",
      "title": "SNAP Data Transparency and Oversight Act of 2026",
      "type": "S",
      "number": "3856",
      "congress": 119,
      "introduced_date": "2026-02-12",
      "latest_action": "Read twice and referred to the Committee on Agriculture, Nutrition, and Forestry.",
      "url": "https://api.congress.gov/v3/bill/119/s/3856?format=json",
      "keywords": [
        "data",
        "secretary",
        "state",
        "program",
        "nutrition",
        "provide",
        "recipient",
        "request",
        "agriculture",
        "food",
        "require",
        "level",
        "oversight",
        "agency",
        "enforcement",
        "purposes",
        "federal",
        "html",
        "body",
        "pre"
      ],
      "has_text": true,
      "similarity_score": null,
      "match_type": "member_bill",
      "alec_match": null,
      "similar_member_bills": [
        {
          "bill_id": "HR6520-119",
          "sponsor_id": "F000475",
          "similarity_score": 0.827
        }
      ],
      "cosponsors": [
        "E000295",
        "T000278"
      ],
      "donor_interest": {
        "match": false,
        "matched_industries": [],
        "keyword_hits": {}
      }
    },
    {
      "bill_id": "S3788-119",
      "title": "CLEAR LABELS Act",
      "type": "S",
      "number": "3788",
      "congress": 119,
      "introduced_date": "2026-02-05",
      "latest_action": "Read twice and referred to the Committee on Health, Education, Labor, and Pensions.",
      "url": "https://api.congress.gov/v3/bill/119/s/3788?format=json",
      "keywords": [
        "drug",
        "manufacturer",
        "information",
        "labeling",
        "original",
        "finished",
        "product",
        "active",
        "pharmaceutical",
        "federal",
        "food",
        "cosmetic",
        "containing",
        "name",
        "place",
        "business",
        "packer",
        "distributor",
        "electronic",
        "ingredient"
      ],
      "has_text": true,
      "similarity_score": null,
      "match_type": null,
      "alec_match": null,
      "similar_member_bills": [],
      "cosponsors": [
        "G000555",
        "T000278",
        "B001319",
        "J000293",
        "M001244"
      ],
      "donor_interest": {
        "match": false,
        "matched_industries": [],
        "keyword_hits": {}
      }
    },
    {
      "bill_id": "-119",
      "title": "",
      "type": "",
      "number": "",
      "congress": 119,
      "introduced_date": "2026-01-29",
      "latest_action": "",
      "url": "https://api.congress.gov/v3/amendment/119/samdt/4265?format=json",
      "keywords": [],
      "has_text": false,
      "similarity_score": null,
      "match_type": null,
      "alec_match": null,
      "similar_member_bills": [],
      "cosponsors": [],
      "donor_interest": {
        "match": false,
        "matched_industries": [],
        "keyword_hits": {}
      }
    }
  ],
  "bills_updated": "2026-03-10T08:18:42.579583+00:00",
  "bills_count": 10,
  "donor_alignment_score": 0.0,
  "alec_match_count": 0,
  "donor_match_count": 0,
  "edgar_status": "unresolved"
}