{
  "votes": [
    {
      "bill": "H.R. 7744: Department of Homeland Security Appropriations Act, 2026",
      "question_text": "",
      "date": "2026-03-05",
      "position": "Nay",
      "result": "Passed",
      "chamber": "House",
      "url": "https://www.govtrack.us/congress/votes/119-2026/h87"
    },
    {
      "bill": "On Motion to Recommit: H.R. 7744: Department of Homeland Security Appropriations Act, 2026",
      "question_text": "",
      "date": "2026-03-05",
      "position": "Yea",
      "result": "Failed",
      "chamber": "House",
      "url": "https://www.govtrack.us/congress/votes/119-2026/h86"
    },
    {
      "bill": "H.Con.Res. 38: Directing the President pursuant to section 5(c) of the War Powers Resolution to remove United States Armed Forces from unauthorized hostilities in the Islamic Republic of Iran.",
      "question_text": "",
      "date": "2026-03-05",
      "position": "Yea",
      "result": "Failed",
      "chamber": "House",
      "url": "https://www.govtrack.us/congress/votes/119-2026/h85"
    },
    {
      "bill": "H.Res. 1099: Reaffirming Iran remains the largest state sponsor of terrorism.",
      "question_text": "",
      "date": "2026-03-05",
      "position": "Yea",
      "result": "Passed",
      "chamber": "House",
      "url": "https://www.govtrack.us/congress/votes/119-2026/h84"
    },
    {
      "bill": "On Motion to Refer: H.Res. 1100: Directing the Committee on Ethics to preserve and publicly release records of the \u2026",
      "question_text": "",
      "date": "2026-03-04",
      "position": "Yea",
      "result": "Passed",
      "chamber": "House",
      "url": "https://www.govtrack.us/congress/votes/119-2026/h83"
    },
    {
      "bill": "H.R. 6472: Territorial Student Access to Higher Education Act",
      "question_text": "",
      "date": "2026-03-04",
      "position": "Yea",
      "result": "Passed",
      "chamber": "House",
      "url": "https://www.govtrack.us/congress/votes/119-2026/h82"
    },
    {
      "bill": "S. 723: Tribal Trust Land Homeownership Act of 2025",
      "question_text": "",
      "date": "2026-03-04",
      "position": "Yea",
      "result": "Passed",
      "chamber": "House",
      "url": "https://www.govtrack.us/congress/votes/119-2026/h81"
    },
    {
      "bill": "H.Res. 1095: Providing for consideration of the bill (H.R. 7744) making appropriations for the Department of Homeland Security for the fiscal year ending September 30, 2026, and for other purposes.",
      "question_text": "",
      "date": "2026-03-04",
      "position": "No",
      "result": "Passed",
      "chamber": "House",
      "url": "https://www.govtrack.us/congress/votes/119-2026/h80"
    },
    {
      "bill": "On Ordering the Previous Question: H.Res. 1095: Providing for consideration of the bill (H.R. 7744) making appropriations for the Department \u2026",
      "question_text": "",
      "date": "2026-03-04",
      "position": "Nay",
      "result": "Passed",
      "chamber": "House",
      "url": "https://www.govtrack.us/congress/votes/119-2026/h79"
    },
    {
      "bill": "H.R. 4758: Homeowner Energy Freedom Act",
      "question_text": "",
      "date": "2026-02-25",
      "position": "Nay",
      "result": "Passed",
      "chamber": "House",
      "url": "https://www.govtrack.us/congress/votes/119-2026/h78"
    },
    {
      "bill": "On Motion to Recommit: H.R. 4758: Homeowner Energy Freedom Act",
      "question_text": "",
      "date": "2026-02-25",
      "position": "Yea",
      "result": "Failed",
      "chamber": "House",
      "url": "https://www.govtrack.us/congress/votes/119-2026/h77"
    },
    {
      "bill": "H.R. 4626: Home Appliance Protection and Affordability Act",
      "question_text": "",
      "date": "2026-02-24",
      "position": "Nay",
      "result": "Passed",
      "chamber": "House",
      "url": "https://www.govtrack.us/congress/votes/119-2026/h76"
    },
    {
      "bill": "On Motion to Recommit: H.R. 4626: Home Appliance Protection and Affordability Act",
      "question_text": "",
      "date": "2026-02-24",
      "position": "Yea",
      "result": "Failed",
      "chamber": "House",
      "url": "https://www.govtrack.us/congress/votes/119-2026/h75"
    },
    {
      "bill": "H.Res. 1075: Providing for consideration of the bill (H.R. 4626) to amend the Energy Policy and Conservation Act to prohibit the Secretary of Energy from prescribing any new or amended energy conservation standard for a product that is not technologicall",
      "question_text": "",
      "date": "2026-02-24",
      "position": "No",
      "result": "Passed",
      "chamber": "House",
      "url": "https://www.govtrack.us/congress/votes/119-2026/h74"
    },
    {
      "bill": "On Ordering the Previous Question: H.Res. 1075: Providing for consideration of the bill (H.R. 4626) to amend the Energy Policy \u2026",
      "question_text": "",
      "date": "2026-02-24",
      "position": "Nay",
      "result": "Passed",
      "chamber": "House",
      "url": "https://www.govtrack.us/congress/votes/119-2026/h73"
    },
    {
      "bill": "S. 2503: ROTOR Act",
      "question_text": "",
      "date": "2026-02-24",
      "position": "Yea",
      "result": "Failed",
      "chamber": "House",
      "url": "https://www.govtrack.us/congress/votes/119-2026/h72"
    },
    {
      "bill": "H.R. 6329: Information Quality Assurance Act of 2025",
      "question_text": "",
      "date": "2026-02-24",
      "position": "Yea",
      "result": "Passed",
      "chamber": "House",
      "url": "https://www.govtrack.us/congress/votes/119-2026/h71"
    },
    {
      "bill": "H.R. 2189: Law-Enforcement Innovate to De-Escalate Act",
      "question_text": "",
      "date": "2026-02-12",
      "position": "Nay",
      "result": "Passed",
      "chamber": "House",
      "url": "https://www.govtrack.us/congress/votes/119-2026/h70"
    },
    {
      "bill": "S. 1383: Safeguard American Voter Eligibility Act",
      "question_text": "",
      "date": "2026-02-11",
      "position": "Nay",
      "result": "Passed",
      "chamber": "House",
      "url": "https://www.govtrack.us/congress/votes/119-2026/h69"
    },
    {
      "bill": "On Motion to Commit: S. 1383: Safeguard American Voter Eligibility Act",
      "question_text": "",
      "date": "2026-02-11",
      "position": "Yea",
      "result": "Failed",
      "chamber": "House",
      "url": "https://www.govtrack.us/congress/votes/119-2026/h68"
    }
  ],
  "govtrack_id": 400623,
  "votes_updated": "2026-03-10T05:41:24.115615",
  "votes_status": "ok",
  "id": "W000797",
  "name": "Debbie Wasserman Schultz",
  "party": "Democratic",
  "state": "Florida",
  "district": "25",
  "chamber": "House",
  "photo_url": "https://bioguide.congress.gov/bioguide/photo/W/W000797.jpg",
  "term_start": "2005-01-01",
  "score": 0,
  "flags": [],
  "updated": "2026-03-10T05:37:47.715766",
  "corporate_insider_signals": 0,
  "edgar_signal_type": "corporate_insider",
  "fec_candidate_id": "H4FL20023",
  "total_raised": 1785364.58,
  "total_spent": 875346.73,
  "pac_contributions": 0,
  "individual_contributions": 1322745.71,
  "cash_on_hand": "1967326.77",
  "total_raised_display": "$1.8M",
  "data_updated": "2026-03-10T06:29:29.408733",
  "last_updated": "2026-03-10T06:29:29.408733",
  "bills": [
    {
      "bill_id": "HR7857-119",
      "title": "No Escaping Justice Act of 2026",
      "type": "HR",
      "number": "7857",
      "congress": 119,
      "introduced_date": "2026-03-05",
      "latest_action": "Referred to the Committee on Foreign Affairs, and in addition to the Committee on the Judiciary, for a period to be subsequently determined by the Speaker, in each case for consideration of such provisions as fall within the jurisdiction of the committee concerned.",
      "url": "https://api.congress.gov/v3/bill/119/hr/7857?format=json",
      "keywords": [
        "person",
        "foreign",
        "president",
        "trafficking",
        "persons",
        "sanctions",
        "committee",
        "epstein",
        "conduct",
        "congressional",
        "knowingly",
        "severe",
        "forms",
        "connection",
        "described",
        "enterprise",
        "appropriate",
        "committees",
        "determines",
        "records"
      ],
      "has_text": true,
      "similarity_score": null,
      "match_type": null,
      "alec_match": null,
      "similar_member_bills": [],
      "cosponsors": [],
      "donor_interest": {
        "match": false,
        "matched_industries": [],
        "keyword_hits": {}
      }
    },
    {
      "bill_id": "HR7856-119",
      "title": "Fair Housing for Survivors Act of 2026",
      "type": "HR",
      "number": "7856",
      "congress": 119,
      "introduced_date": "2026-03-05",
      "latest_action": "Referred to the House Committee on the Judiciary.",
      "url": "https://api.congress.gov/v3/bill/119/hr/7856?format=json",
      "keywords": [
        "violence",
        "sexual",
        "domestic",
        "trafficking",
        "assault",
        "forms",
        "survivors",
        "severe",
        "national",
        "origin",
        "survivor",
        "persons",
        "housing",
        "inserting",
        "women",
        "person",
        "striking",
        "whether",
        "sex",
        "fair"
      ],
      "has_text": true,
      "similarity_score": null,
      "match_type": null,
      "alec_match": null,
      "similar_member_bills": [],
      "cosponsors": [
        "M000317",
        "A000370",
        "B001300",
        "B001281",
        "B001324",
        "B000490",
        "B001278",
        "B001315",
        "C001072",
        "C001080"
      ],
      "donor_interest": {
        "match": false,
        "matched_industries": [],
        "keyword_hits": {}
      }
    },
    {
      "bill_id": "HR7564-119",
      "title": "Jaime\u2019s Law",
      "type": "HR",
      "number": "7564",
      "congress": 119,
      "introduced_date": "2026-02-12",
      "latest_action": "Referred to the House Committee on the Judiciary.",
      "url": "https://api.congress.gov/v3/bill/119/hr/7564?format=json",
      "keywords": [
        "ammunition",
        "transfer",
        "inserting",
        "licensed",
        "striking",
        "person",
        "transferee",
        "code",
        "matter",
        "possession",
        "prevent",
        "subparagraph",
        "preceding",
        "licensee",
        "prohibited",
        "purpose",
        "place",
        "importer",
        "manufacturer",
        "dealer"
      ],
      "has_text": true,
      "similarity_score": null,
      "match_type": null,
      "alec_match": null,
      "similar_member_bills": [],
      "cosponsors": [
        "M001217",
        "F000462",
        "C001066",
        "N000191",
        "B001300",
        "P000608",
        "J000288",
        "S001156",
        "L000582",
        "K000375"
      ],
      "donor_interest": {
        "match": false,
        "matched_industries": [],
        "keyword_hits": {}
      }
    },
    {
      "bill_id": "HCONRES69-119",
      "title": "Recognizing the 15th Anniversary of the January 8, 2011, Tucson, Arizona, shooting and honoring the survivors, victims, and former Congresswoman Gabby Giffords, a gun violence survivor, and one of the Nation's most influential voices of courage in the fight to end gun violence.",
      "type": "HCONRES",
      "number": "69",
      "congress": 119,
      "introduced_date": "2026-01-08",
      "latest_action": "Referred to the House Committee on Oversight and Government Reform.",
      "url": "https://api.congress.gov/v3/bill/119/hconres/69?format=json",
      "keywords": [
        "mrs",
        "congresswoman",
        "giffords",
        "violence",
        "gabby",
        "gun",
        "arizona",
        "january",
        "tucson",
        "texas",
        "congressional",
        "former",
        "nation",
        "courage",
        "illinois",
        "new",
        "york",
        "district",
        "attack",
        "survivors"
      ],
      "has_text": true,
      "similarity_score": null,
      "match_type": null,
      "alec_match": null,
      "similar_member_bills": [],
      "cosponsors": [
        "F000466",
        "J000294",
        "C001101",
        "A000371",
        "L000582",
        "A000380",
        "A000381",
        "A000148",
        "B001318",
        "B001300"
      ],
      "donor_interest": {
        "match": false,
        "matched_industries": [],
        "keyword_hits": {}
      }
    },
    {
      "bill_id": "HRES904-119",
      "title": "Recognizing November 30, 2025, as \"Yom Haplitim\" or \"Jewish Refugee Day\".",
      "type": "HRES",
      "number": "904",
      "congress": 119,
      "introduced_date": "2025-11-20",
      "latest_action": "Referred to the Committee on the Judiciary, and in addition to the Committees on Education and Workforce, and Foreign Affairs, for a period to be subsequently determined by the Speaker, in each case for consideration of such provisions as fall within the jurisdiction of the committee concerned.",
      "url": "https://api.congress.gov/v3/bill/119/hres/904?format=json",
      "keywords": [
        "jewish",
        "people",
        "november",
        "day",
        "yom",
        "haplitim",
        "refugee",
        "arab",
        "world",
        "israel",
        "war",
        "html",
        "body",
        "pre",
        "res",
        "recognizing",
        "resolution",
        "committee",
        "years",
        "state"
      ],
      "has_text": true,
      "similarity_score": null,
      "match_type": null,
      "alec_match": null,
      "similar_member_bills": [],
      "cosponsors": [
        "G000601",
        "S001190"
      ],
      "donor_interest": {
        "match": false,
        "matched_industries": [],
        "keyword_hits": {}
      }
    },
    {
      "bill_id": "HR5506-119",
      "title": "Courtney Wild Reinforcing Crime Victims\u2019 Rights Act",
      "type": "HR",
      "number": "5506",
      "congress": 119,
      "introduced_date": "2025-09-18",
      "latest_action": "Referred to the House Committee on the Judiciary.",
      "url": "https://api.congress.gov/v3/bill/119/hr/5506?format=json",
      "keywords": [
        "crime",
        "victim",
        "court",
        "rights",
        "general",
        "government",
        "district",
        "victims",
        "right",
        "case",
        "attorney",
        "administrative",
        "authority",
        "information",
        "iii",
        "described",
        "order",
        "motion",
        "department",
        "justice"
      ],
      "has_text": true,
      "similarity_score": null,
      "match_type": null,
      "alec_match": null,
      "similar_member_bills": [],
      "cosponsors": [
        "B001309",
        "S000168",
        "F000462"
      ],
      "donor_interest": {
        "match": false,
        "matched_industries": [],
        "keyword_hits": {}
      }
    },
    {
      "bill_id": "HR4752-119",
      "title": "Reducing Hereditary Cancer Act",
      "type": "HR",
      "number": "4752",
      "congress": 119,
      "introduced_date": "2025-07-23",
      "latest_action": "Referred to the Committee on Energy and Commerce, and in addition to the Committee on Ways and Means, for a period to be subsequently determined by the Speaker, in each case for consideration of such provisions as fall within the jurisdiction of the committee concerned.",
      "url": "https://api.congress.gov/v3/bill/119/hr/4752?format=json",
      "keywords": [
        "cancer",
        "hereditary",
        "mutation",
        "testing",
        "individuals",
        "risk",
        "subparagraph",
        "based",
        "history",
        "coverage",
        "germline",
        "end",
        "evidence",
        "social",
        "security",
        "gene",
        "genetic",
        "screenings",
        "case",
        "guidelines"
      ],
      "has_text": true,
      "similarity_score": null,
      "match_type": null,
      "alec_match": null,
      "similar_member_bills": [],
      "cosponsors": [
        "M001215",
        "S001216",
        "B001260",
        "C001068",
        "D000624",
        "G000583",
        "S001231",
        "C001072",
        "N000147",
        "B001278"
      ],
      "donor_interest": {
        "match": false,
        "matched_industries": [],
        "keyword_hits": {}
      }
    },
    {
      "bill_id": "HR4751-119",
      "title": "To amend the Virginia Graeme Baker Pool and Spa Safety Act to reauthorize certain programs, and for other purposes.",
      "type": "HR",
      "number": "4751",
      "congress": 119,
      "introduced_date": "2025-07-23",
      "latest_action": "Referred to the House Committee on Energy and Commerce.",
      "url": "https://api.congress.gov/v3/bill/119/hr/4751?format=json",
      "keywords": [
        "pool",
        "safety",
        "virginia",
        "graeme",
        "baker",
        "spa",
        "certain",
        "programs",
        "html",
        "body",
        "pre",
        "introduced",
        "reauthorize",
        "purposes",
        "bill",
        "program",
        "fiscal",
        "years",
        "congressional",
        "bills"
      ],
      "has_text": true,
      "similarity_score": null,
      "match_type": null,
      "alec_match": null,
      "similar_member_bills": [],
      "cosponsors": [
        "C001051",
        "N000188",
        "F000466",
        "G000583",
        "C001072",
        "C001119",
        "F000462",
        "M001217"
      ],
      "donor_interest": {
        "match": false,
        "matched_industries": [],
        "keyword_hits": {}
      }
    },
    {
      "bill_id": "HR4541-119",
      "title": "EARLY Act Reauthorization of 2025",
      "type": "HR",
      "number": "4541",
      "congress": 119,
      "introduced_date": "2025-07-17",
      "latest_action": "Referred to the House Committee on Energy and Commerce.",
      "url": "https://api.congress.gov/v3/bill/119/hr/4541?format=json",
      "keywords": [
        "young",
        "health",
        "women",
        "breast",
        "education",
        "awareness",
        "requires",
        "learning",
        "mrs",
        "html",
        "body",
        "pre",
        "introduced",
        "reauthorize",
        "bill",
        "reauthorization",
        "congressional",
        "bills",
        "government",
        "publishing"
      ],
      "has_text": true,
      "similarity_score": null,
      "match_type": null,
      "alec_match": null,
      "similar_member_bills": [],
      "cosponsors": [
        "M001215",
        "C001066",
        "F000466",
        "D000624",
        "H001086",
        "N000147",
        "G000583",
        "E000301",
        "G000599",
        "R000305"
      ],
      "donor_interest": {
        "match": false,
        "matched_industries": [],
        "keyword_hits": {}
      }
    },
    {
      "bill_id": "HR4542-119",
      "title": "No Cages in the Everglades Act",
      "type": "HR",
      "number": "4542",
      "congress": 119,
      "introduced_date": "2025-07-17",
      "latest_action": "Referred to the Committee on the Judiciary, and in addition to the Committee on Homeland Security, for a period to be subsequently determined by the Speaker, in each case for consideration of such provisions as fall within the jurisdiction of the committee concerned.",
      "url": "https://api.congress.gov/v3/bill/119/hr/4542?format=json",
      "keywords": [
        "facility",
        "committee",
        "security",
        "congressional",
        "homeland",
        "everglades",
        "department",
        "detention",
        "immigration",
        "described",
        "operation",
        "general",
        "individuals",
        "staff",
        "standards",
        "government",
        "florida",
        "construction",
        "designated",
        "report"
      ],
      "has_text": true,
      "similarity_score": null,
      "match_type": null,
      "alec_match": null,
      "similar_member_bills": [],
      "cosponsors": [
        "F000476",
        "C001066",
        "S001200",
        "F000462",
        "W000808",
        "C001127",
        "M001217",
        "N000147",
        "J000288",
        "C001130"
      ],
      "donor_interest": {
        "match": false,
        "matched_industries": [],
        "keyword_hits": {}
      }
    }
  ],
  "bills_updated": "2026-03-10T08:45:24.937984+00:00",
  "bills_count": 10,
  "donor_alignment_score": 0.0,
  "alec_match_count": 0,
  "donor_match_count": 0,
  "edgar_status": "unresolved"
}